{
	"type": "origins:multiple",
	"blind": 
	{
		"type": "origins:stacking_status_effect",
		"min_stacks": "0",
		"max_stacks": "1",
		"duration_per_stack": "20",
		"effect": 
		{
			"effect": "minecraft:blindness",
			"duration": 100,
			"is_ambient": true,
			"show_particles": false,
			"show_icon": true
		},
		"condition": 
		{
			"type": "origins:power_active",
			"power": "*:shulkingknight/rage_toggle"
		}
	},
	"speed": 
	{
		"type": "origins:stacking_status_effect",
		"min_stacks": "0",
		"max_stacks": "1",
		"duration_per_stack": "20",
		"effect": 
		{
			"effect": "minecraft:speed",
			"duration": 100,
			"amplifier": 1,
			"is_ambient": true,
			"show_particles": false,
			"show_icon": true
		},
		"condition": 
		{
			"type": "origins:power_active",
			"power": "*:shulkingknight/rage_toggle"
		}
	},
    "strength": 
	{
		"type": "origins:stacking_status_effect",
		"min_stacks": "0",
		"max_stacks": "1",
		"duration_per_stack": "20",
		"effect": 
		{
			"effect": "minecraft:strength",
			"duration": 100,
			"amplifier": 2,
			"is_ambient": true,
			"show_particles": false,
			"show_icon": true
		},
		"condition": 
		{
			"type": "origins:power_active",
			"power": "*:shulkingknight/rage_toggle"
		}
	},
	"hidden": true
}